__init__.py
mcp_1c/__init__.py
mcp_1c/cache.py
mcp_1c/client.py
mcp_1c/server.py
mcp_1c/tools.py
mcp_1c-0.1.0.1.dist-info/METADATA
mcp_1c-0.1.0.1.dist-info/WHEEL
mcp_1c-0.1.0.1.dist-info/top_level.txt
mcp_1c-0.1.0.1.dist-info/RECORD
