Metadata-Version: 2.4
Name: mcp-1c
Version: 0.1.0.1
Summary: MCP сервер для работы с 1С через протокол OData
Requires-Python: >=3.12
Requires-Dist: fastmcp>=2.12.4
Requires-Dist: httpx>=0.28.1
Requires-Dist: loguru>=0.7.3
Requires-Dist: pydantic>=2.11.9
Requires-Dist: python-dateutil>=2.9.0.post0
Requires-Dist: xmltodict>=1.0.2
